[
  {
    "validationAuthority": [
      {
        "type": "LEIauthority",
        "validationAuthorityID": "RA000002",
        "otherValidationAuthorityID": "BJFH8O7U",
        "validationAuthorityEntityID": "1MNR9R1C89SSUDHWE2Z2"
      }
    ],
    "monitor": "calculate",
    "bus": "copy",
    "alarm": "bypass"
  },
  {
    "type": "LEIregistration",
    "validationSources": "PARTIALLY_CORROBORATED",
    "matrix": "parse",
    "capacitor": "calculate"
  },
  {
    "@context": [
      "https://w3id.org/traceability/v1"
    ],
    "type": "LEIregistration",
    "initialRegistrationDate": "2020-01-01",
    "lastUpdateDate": "2020-01-01",
    "status": "IN PROGRESS",
    "nextRenewalDate": "2021-02-02",
    "managingLou": "DBRFNNSYJVIVMHWLBMUE",
    "validationAuthority": [
      {
        "type": "LEIauthority",
        "validationAuthorityID": "RA000003",
        "otherValidationAuthorityID": "VAF4OUWD",
        "validationAuthorityEntityID": "UNEG472LK2NEUJAF6QDT"
      }
    ],
    "transmitter": "compress",
    "array": "compress",
    "feed": "bypass",
    "panel": "reboot"
  }
]