{
  "@context": [
    "https://www.w3.org/2018/credentials/v1",
    "https://w3id.org/traceability/v1"
  ],
  "id": "http://example.org/credentials/",
  "type": [
    "VerifiableCredential"
  ],
  "issuanceDate": "2021-02-04T20:29:37+00:00",
  "issuer": "did:example:123",
  "credentialSubject": {
    "@context": [
      "https://w3id.org/traceability/v1"
    ],
    "type": "LEIevidenceDocument",
    "lei": "057ISY7L2ZHU013NTARK",
    "entity": {
      "@context": [
        "https://w3id.org/traceability/v1"
      ],
      "type": "LEIentity",
      "legalName": "Effertz - Kozey",
      "legalNameLanguage": "nl_BE",
      "otherNames": [
        "Wuckert LLC",
        "Rippin Inc"
      ],
      "transliteratedOtherNames": [
        "Wuckert LLC",
        "Rippin Inc"
      ],
      "legalAddress": {
        "type": "LEIaddress",
        "language": "zh_CN",
        "addressLines": [
          "Padberg Inc",
          "803 Ryann Island"
        ],
        "addressNumber": "365",
        "addressNumberWithinBuilding": "1",
        "mailRouting": "2919 Ernser Heights, 92864",
        "city": "Bergeview",
        "region": "Cambridgeshire",
        "country": "Tunisia",
        "postalCode": "66198-5932"
      },
      "headquartersAddress": {
        "type": "LEIaddress",
        "language": "ge",
        "addressLines": [
          "Wuckert - Bogan",
          "17473 Jayne Harbors"
        ],
        "addressNumber": "336",
        "addressNumberWithinBuilding": "6",
        "mailRouting": "2027 Eden Brooks, 50072",
        "city": "Thompsonberg",
        "region": "Borders",
        "country": "Paraguay",
        "postalCode": "36145-6113"
      },
      "registrationAuthority": {
        "type": "LEIauthority",
        "validationAuthorityID": "RA000004",
        "otherValidationAuthorityID": "TP4KNDCF",
        "validationAuthorityEntityID": "QKJ0G26VM2ZPTX29DDXK"
      },
      "legalJurisdiction": "Buckinghamshire",
      "entityCategory": "Finance",
      "legalForm": "LLC",
      "associatedEntity": {
        "type": "Organization",
        "leiCode": "WAUCOX17SVU1S3IU8MUQ",
        "name": "Veum, Ritchie and Swift"
      },
      "status": "REQUESTED",
      "expirationDate": "2022-07-11",
      "expirationReason": "syndicate open-source content",
      "successorEntity": {
        "type": "Organization",
        "leiCode": "ECGP1A68SCG6APDMUHQE",
        "name": "Upton Inc"
      },
      "otherAddresses": []
    },
    "registration": {
      "@context": [
        "https://w3id.org/traceability/v1"
      ],
      "type": "LEIregistration",
      "initialRegistrationDate": "2020-01-01",
      "lastUpdateDate": "2020-01-01",
      "status": "IN PROGRESS",
      "nextRenewalDate": "2021-02-02",
      "managingLou": "PGBARCNSRFPJKNFSHCNK",
      "validationSources": "PARTIALLY_CORROBORATED",
      "validationAuthority": [
        {
          "type": "LEIauthority",
          "validationAuthorityID": "RA000001",
          "otherValidationAuthorityID": "19RXWKGJ",
          "validationAuthorityEntityID": "JLYD7TIIH494TJWXSB7V"
        }
      ]
    },
    "bic": [
      "MUOTSMDXJK"
    ]
  }
}